TFMongoDB-0.1.3.data/purelib/tfmongodb/__init__.py
TFMongoDB-0.1.3.data/purelib/tfmongodb/__init__2.py
TFMongoDB-0.1.3.data/purelib/tfmongodb/libTFMongoDB.dylib
TFMongoDB-0.1.3.data/purelib/tfmongodb/test_op.py
TFMongoDB-0.1.3.dist-info/LICENSE.txt
TFMongoDB-0.1.3.dist-info/METADATA
TFMongoDB-0.1.3.dist-info/WHEEL
TFMongoDB-0.1.3.dist-info/top_level.txt
TFMongoDB-0.1.3.dist-info/RECORD
