Metadata-Version: 2.1
Name: TFMongoDB
Version: 0.1.3
Summary: A Tensorflow MongoDB connector
Home-page: https://tfmongodb.org
Author: Sven Boesiger
Author-email: ronnysven@gmail.com
License: UNKNOWN
Keywords: tensorflow mongodb datascience
Platform: UNKNOWN
Classifier: Development Status :: 3 - Alpha
Classifier: Intended Audience :: Developers
Classifier: Topic :: Software Development :: Build Tools
Classifier: License :: OSI Approved :: Apache Software License
Classifier: Programming Language :: Python :: 2
Classifier: Programming Language :: Python :: 2.7
Classifier: Programming Language :: Python :: 3
Classifier: Programming Language :: Python :: 3.4
Classifier: Programming Language :: Python :: 3.5
Classifier: Programming Language :: Python :: 3.6
Requires-Dist: tensorflow
